telepath/__init__.py
telepath/test_settings.py
telepath/tests.py
telepath/static/telepath/js/telepath.js
telepath-0.3.1.dist-info/LICENSE
telepath-0.3.1.dist-info/METADATA
telepath-0.3.1.dist-info/WHEEL
telepath-0.3.1.dist-info/top_level.txt
telepath-0.3.1.dist-info/RECORD
