Metadata-Version: 2.1
Name: telepath
Version: 0.3.1
Summary: A library for exchanging data between Python and JavaScript
Home-page: https://github.com/wagtail/telepath
Author: Matthew Westcott
Author-email: matthew.westcott@torchbox.com
License: BSD
Classifier: Development Status :: 5 - Production/Stable
Classifier: Environment :: Web Environment
Classifier: Intended Audience :: Developers
Classifier: License :: OSI Approved :: BSD License
Classifier: Operating System :: OS Independent
Classifier: Programming Language :: Python
Classifier: Programming Language :: Python :: 3
Classifier: Programming Language :: Python :: 3 :: Only
Classifier: Framework :: Django
Requires-Python: >=3.8
Provides-Extra: docs
License-File: LICENSE
